smart_log_rotation/__init__.py
smart_log_rotation/__main__.py
starlyng_smart_log_rotation-0.0.2.dist-info/METADATA
starlyng_smart_log_rotation-0.0.2.dist-info/WHEEL
starlyng_smart_log_rotation-0.0.2.dist-info/entry_points.txt
starlyng_smart_log_rotation-0.0.2.dist-info/top_level.txt
starlyng_smart_log_rotation-0.0.2.dist-info/RECORD
