Metadata-Version: 2.1
Name: starlyng-smart-log-rotation
Version: 0.0.2
Summary: Manage servers by rotating logs after a certain amount of time.
Home-page: https://github.com/starlyngapp/smart-log-rotation
Author: Justin Sherwood
Author-email: justin@sherwood.fm
License: MIT
Keywords: log rotation ssh remote server management automation system administration devops log management
Platform: UNKNOWN
Classifier: Development Status :: 3 - Alpha
Classifier: Intended Audience :: Developers
Classifier: Topic :: System :: Systems Administration
Classifier: Programming Language :: Python :: 3
Classifier: Programming Language :: Python :: 3.7
Classifier: Programming Language :: Python :: 3.8
Classifier: Programming Language :: Python :: 3.9
Classifier: Programming Language :: Python :: 3.10
Classifier: Operating System :: OS Independent
Classifier: License :: OSI Approved :: MIT License
Requires-Python: >=3.7
Requires-Dist: python-dotenv
Provides-Extra: dev
Requires-Dist: pytest; extra == "dev"
Requires-Dist: pytest-mock==3.14.0; extra == "dev"
Requires-Dist: pylint==3.2.2; extra == "dev"
Requires-Dist: twine; extra == "dev"
Requires-Dist: wheel; extra == "dev"
